<?xml version="1.0" encoding="utf-8" ?>
<dwsync>
<file name="shot1.jpg" server="orion.servers.rbl-mer.misp.co.uk//public_html/" local="127520068410000000" remote="129787876800000000" />
<file name="shot10.jpg" server="orion.servers.rbl-mer.misp.co.uk//public_html/" local="127520070280000000" remote="129787876800000000" />
<file name="shot10_thumbnail.jpg" server="orion.servers.rbl-mer.misp.co.uk//public_html/" local="129793141624153223" remote="129793141200000000" />
<file name="shot11.jpg" server="orion.servers.rbl-mer.misp.co.uk//public_html/" local="127520070430000000" remote="129787876800000000" />
<file name="shot11_thumbnail.jpg" server="orion.servers.rbl-mer.misp.co.uk//public_html/" local="129793141624383237" remote="129793141200000000" />
<file name="shot12.jpg" server="orion.servers.rbl-mer.misp.co.uk//public_html/" local="127520070890000000" remote="129787876800000000" />
<file name="shot12_thumbnail.jpg" server="orion.servers.rbl-mer.misp.co.uk//public_html/" local="129793141624593249" remote="129793141200000000" />
<file name="shot13.jpg" server="orion.servers.rbl-mer.misp.co.uk//public_html/" local="127520070800000000" remote="129787876800000000" />
<file name="shot13_thumbnail.jpg" server="orion.servers.rbl-mer.misp.co.uk//public_html/" local="129793141624823262" remote="129793141200000000" />
<file name="shot14.jpg" server="orion.servers.rbl-mer.misp.co.uk//public_html/" local="127520071020000000" remote="129787876800000000" />
<file name="shot14_thumbnail.jpg" server="orion.servers.rbl-mer.misp.co.uk//public_html/" local="129793141625103278" remote="129793141200000000" />
<file name="shot15.jpg" server="orion.servers.rbl-mer.misp.co.uk//public_html/" local="127520071130000000" remote="129787876800000000" />
<file name="shot15_thumbnail.jpg" server="orion.servers.rbl-mer.misp.co.uk//public_html/" local="129793141625383294" remote="129793141200000000" />
<file name="shot16.jpg" server="orion.servers.rbl-mer.misp.co.uk//public_html/" local="127520071200000000" remote="129787876800000000" />
<file name="shot16_thumbnail.jpg" server="orion.servers.rbl-mer.misp.co.uk//public_html/" local="129793141625663310" remote="129793141200000000" />
<file name="shot17.jpg" server="orion.servers.rbl-mer.misp.co.uk//public_html/" local="127520071410000000" remote="129787876800000000" />
<file name="shot17_thumbnail.jpg" server="orion.servers.rbl-mer.misp.co.uk//public_html/" local="129793141625943326" remote="129793141200000000" />
<file name="shot18.jpg" server="orion.servers.rbl-mer.misp.co.uk//public_html/" local="127520071950000000" remote="129787876800000000" />
<file name="shot18_thumbnail.jpg" server="orion.servers.rbl-mer.misp.co.uk//public_html/" local="129793141626193340" remote="129793141200000000" />
<file name="shot19.jpg" server="orion.servers.rbl-mer.misp.co.uk//public_html/" local="127520072020000000" remote="129787876800000000" />
<file name="shot19_thumbnail.jpg" server="orion.servers.rbl-mer.misp.co.uk//public_html/" local="129793141626453355" remote="129793141200000000" />
<file name="shot1_thumbnail.jpg" server="orion.servers.rbl-mer.misp.co.uk//public_html/" local="129793141623903209" remote="129793141200000000" />
<file name="shot2.jpg" server="orion.servers.rbl-mer.misp.co.uk//public_html/" local="127520068540000000" remote="129787876800000000" />
<file name="shot20.jpg" server="orion.servers.rbl-mer.misp.co.uk//public_html/" local="127520072090000000" remote="129787876800000000" />
<file name="shot20_thumbnail.jpg" server="orion.servers.rbl-mer.misp.co.uk//public_html/" local="129793141626943383" remote="129793141200000000" />
<file name="shot21.jpg" server="orion.servers.rbl-mer.misp.co.uk//public_html/" local="127520072160000000" remote="129787876800000000" />
<file name="shot21_thumbnail.jpg" server="orion.servers.rbl-mer.misp.co.uk//public_html/" local="129793141627193397" remote="129793141200000000" />
<file name="shot22.jpg" server="orion.servers.rbl-mer.misp.co.uk//public_html/" local="127520072240000000" remote="129787876800000000" />
<file name="shot22_thumbnail.jpg" server="orion.servers.rbl-mer.misp.co.uk//public_html/" local="129793141627443412" remote="129793141200000000" />
<file name="shot23.jpg" server="orion.servers.rbl-mer.misp.co.uk//public_html/" local="127520073010000000" remote="129787876800000000" />
<file name="shot23_thumbnail.jpg" server="orion.servers.rbl-mer.misp.co.uk//public_html/" local="129793141627693426" remote="129793141200000000" />
<file name="shot24.jpg" server="orion.servers.rbl-mer.misp.co.uk//public_html/" local="127520073110000000" remote="129787876800000000" />
<file name="shot24_thumbnail.jpg" server="orion.servers.rbl-mer.misp.co.uk//public_html/" local="129793141627943440" remote="129793141200000000" />
<file name="shot25.jpg" server="orion.servers.rbl-mer.misp.co.uk//public_html/" local="127520073190000000" remote="129787876800000000" />
<file name="shot25_thumbnail.jpg" server="orion.servers.rbl-mer.misp.co.uk//public_html/" local="129793141628193455" remote="129793141200000000" />
<file name="shot2_thumbnail.jpg" server="orion.servers.rbl-mer.misp.co.uk//public_html/" local="129793141626703369" remote="129793141200000000" />
<file name="shot4.jpg" server="orion.servers.rbl-mer.misp.co.uk//public_html/" local="127520068850000000" remote="129787876800000000" />
<file name="shot4_thumbnail.jpg" server="orion.servers.rbl-mer.misp.co.uk//public_html/" local="129793141628453469" remote="129793141200000000" />
<file name="shot5.jpg" server="orion.servers.rbl-mer.misp.co.uk//public_html/" local="127520069770000000" remote="129787877400000000" />
<file name="shot5_thumbnail.jpg" server="orion.servers.rbl-mer.misp.co.uk//public_html/" local="129793141628703484" remote="129793141200000000" />
<file name="shot6.jpg" server="orion.servers.rbl-mer.misp.co.uk//public_html/" local="127520069990000000" remote="129787877400000000" />
<file name="shot6_thumbnail.jpg" server="orion.servers.rbl-mer.misp.co.uk//public_html/" local="129793141628983500" remote="129793141200000000" />
<file name="shot7.jpg" server="orion.servers.rbl-mer.misp.co.uk//public_html/" local="127520070070000000" remote="129787877400000000" />
<file name="shot7_thumbnail.jpg" server="orion.servers.rbl-mer.misp.co.uk//public_html/" local="129793141629283517" remote="129793141200000000" />
<file name="shot8.jpg" server="orion.servers.rbl-mer.misp.co.uk//public_html/" local="127520070140000000" remote="129787877400000000" />
<file name="shot8_thumbnail.jpg" server="orion.servers.rbl-mer.misp.co.uk//public_html/" local="129793141629573533" remote="129793141200000000" />
<file name="shot9.jpg" server="orion.servers.rbl-mer.misp.co.uk//public_html/" local="127520070210000000" remote="129787877400000000" />
<file name="shot9_thumbnail.jpg" server="orion.servers.rbl-mer.misp.co.uk//public_html/" local="129793141629853550" remote="129793141200000000" />
<file name="wgcEditor1.jpg" server="orion.servers.rbl-mer.misp.co.uk//public_html/" local="129115071120000000" remote="129787877400000000" />
<file name="wgcEditor10.jpg" server="orion.servers.rbl-mer.misp.co.uk//public_html/" local="129115072190000000" remote="129787877400000000" />
<file name="wgcEditor10_thumbnail.jpg" server="orion.servers.rbl-mer.misp.co.uk//public_html/" local="129793141630693598" remote="129793141200000000" />
<file name="wgcEditor11.jpg" server="orion.servers.rbl-mer.misp.co.uk//public_html/" local="129115072270000000" remote="129787877400000000" />
<file name="wgcEditor11_thumbnail.jpg" server="orion.servers.rbl-mer.misp.co.uk//public_html/" local="129793141631153624" remote="129793141200000000" />
<file name="wgcEditor12.jpg" server="orion.servers.rbl-mer.misp.co.uk//public_html/" local="129115072340000000" remote="129787877400000000" />
<file name="wgcEditor12_thumbnail.jpg" server="orion.servers.rbl-mer.misp.co.uk//public_html/" local="129793141631633651" remote="129793141200000000" />
<file name="wgcEditor13.jpg" server="orion.servers.rbl-mer.misp.co.uk//public_html/" local="129115072420000000" remote="129787877400000000" />
<file name="wgcEditor13_thumbnail.jpg" server="orion.servers.rbl-mer.misp.co.uk//public_html/" local="129793141632083677" remote="129793141200000000" />
<file name="wgcEditor14.jpg" server="orion.servers.rbl-mer.misp.co.uk//public_html/" local="129115072520000000" remote="129787877400000000" />
<file name="wgcEditor14_thumbnail.jpg" server="orion.servers.rbl-mer.misp.co.uk//public_html/" local="129793141632523702" remote="129793141200000000" />
<file name="wgcEditor1_thumbnail.jpg" server="orion.servers.rbl-mer.misp.co.uk//public_html/" local="129793141630223571" remote="129793141200000000" />
<file name="wgcEditor2.jpg" server="orion.servers.rbl-mer.misp.co.uk//public_html/" local="129115071230000000" remote="129787877400000000" />
<file name="wgcEditor2_thumbnail.jpg" server="orion.servers.rbl-mer.misp.co.uk//public_html/" local="129793141632943726" remote="129793141200000000" />
<file name="wgcEditor3.jpg" server="orion.servers.rbl-mer.misp.co.uk//public_html/" local="129115071330000000" remote="129787877400000000" />
<file name="wgcEditor3_thumbnail.jpg" server="orion.servers.rbl-mer.misp.co.uk//public_html/" local="129793141633373751" remote="129793141200000000" />
<file name="wgcEditor4.jpg" server="orion.servers.rbl-mer.misp.co.uk//public_html/" local="129115071430000000" remote="129787877400000000" />
<file name="wgcEditor4_thumbnail.jpg" server="orion.servers.rbl-mer.misp.co.uk//public_html/" local="129793141633823777" remote="129793141200000000" />
<file name="wgcEditor5.jpg" server="orion.servers.rbl-mer.misp.co.uk//public_html/" local="129115071680000000" remote="129787877400000000" />
<file name="wgcEditor5_thumbnail.jpg" server="orion.servers.rbl-mer.misp.co.uk//public_html/" local="129793141634263802" remote="129793141200000000" />
<file name="wgcEditor6.jpg" server="orion.servers.rbl-mer.misp.co.uk//public_html/" local="129115071780000000" remote="129787877400000000" />
<file name="wgcEditor6_thumbnail.jpg" server="orion.servers.rbl-mer.misp.co.uk//public_html/" local="129793141634733829" remote="129793141200000000" />
<file name="wgcEditor7.jpg" server="orion.servers.rbl-mer.misp.co.uk//public_html/" local="129115071880000000" remote="129787877400000000" />
<file name="wgcEditor7_thumbnail.jpg" server="orion.servers.rbl-mer.misp.co.uk//public_html/" local="129793141635203856" remote="129793141200000000" />
<file name="wgcEditor8.jpg" server="orion.servers.rbl-mer.misp.co.uk//public_html/" local="129115071960000000" remote="129787877400000000" />
<file name="wgcEditor8_thumbnail.jpg" server="orion.servers.rbl-mer.misp.co.uk//public_html/" local="129793141635633880" remote="129793141200000000" />
<file name="wgcEditor9.jpg" server="orion.servers.rbl-mer.misp.co.uk//public_html/" local="129115072050000000" remote="129787877400000000" />
<file name="wgcEditor9_thumbnail.jpg" server="orion.servers.rbl-mer.misp.co.uk//public_html/" local="129793141636003901" remote="129793141200000000" />
<file name="main.jpg" server="orion.servers.rbl-mer.misp.co.uk//public_html/" local="127520068760000000" remote="129793102800000000" />
<file name="main_thumbnail.jpg" server="orion.servers.rbl-mer.misp.co.uk//public_html/" local="129793141623653195" remote="129793141200000000" />
</dwsync>